airun/__init__.py
airun/__main__.py
airun/cli.py
airun/core/__init__.py
airun/core/ai_fixer.py
airun/core/config.py
airun/core/detector.py
airun/core/llm_router.py
airun/core/runners.py
airun/providers/__init__.py
airun/providers/base.py
airun/providers/claude.py
airun/providers/ollama.py
airun/providers/openai.py
airun/templates/config/default.yaml
airun/templates/prompts/nodejs.txt
airun/templates/prompts/php.txt
airun/templates/prompts/python.txt
airun/templates/prompts/shell.txt
airun/utils/__init__.py
airun/utils/analyzer.py
airun/utils/batch_executor.py
airun/utils/cleaner.py
airun/utils/examples.py
airun/utils/file_ops.py
airun/utils/log_viewer.py
airun/utils/logging.py
airun/utils/validation.py
airun/web/__init__.py
airun/web/app.py
airun-0.1.1.dist-info/LICENSE
airun-0.1.1.dist-info/METADATA
airun-0.1.1.dist-info/WHEEL
airun-0.1.1.dist-info/entry_points.txt
airun-0.1.1.dist-info/RECORD
