Metadata-Version: 2.3
Name: airun
Version: 0.1.1
Summary: AI-Enhanced Universal Script Runner with automatic error fixing
License: MIT
Keywords: ai,automation,scripting,llm,debugging
Author: Your Name
Author-email: your.email@example.com
Requires-Python: >=3.8,<4.0
Classifier: Development Status :: 4 - Beta
Classifier: Intended Audience :: Developers
Classifier: License :: OSI Approved :: MIT License
Classifier: Operating System :: OS Independent
Classifier: Programming Language :: Python :: 3
Classifier: Programming Language :: Python :: 3.8
Classifier: Programming Language :: Python :: 3.9
Classifier: Programming Language :: Python :: 3.10
Classifier: Programming Language :: Python :: 3.11
Classifier: Programming Language :: Python :: 3.12
Classifier: Programming Language :: Python :: 3.13
Classifier: Topic :: Software Development :: Debuggers
Classifier: Topic :: System :: Shells
Classifier: Topic :: Utilities
Provides-Extra: all
Provides-Extra: mqtt
Requires-Dist: asyncio-mqtt (>=0.16.0,<0.17.0) ; extra == "mqtt" or extra == "all"
Requires-Dist: click (>=8.1.0,<9.0.0)
Requires-Dist: httpx (>=0.26.0,<0.27.0)
Requires-Dist: pydantic (>=2.5.0,<3.0.0)
Requires-Dist: pyyaml (>=6.0,<7.0)
Requires-Dist: requests (>=2.31.0,<3.0.0)
Requires-Dist: rich (>=13.7.0,<14.0.0)
Project-URL: Documentation, https://airun.readthedocs.io
Project-URL: Homepage, https://github.com/yourusername/airun
Project-URL: Repository, https://github.com/yourusername/airun
